bshlocal/__init__.py
bshlocal/api.py
bshlocal/device.py
bshlocal/device_service.py
bshlocal/room.py
bshlocal/services_impl.py
bshlocal/session.py
bshlocal-0.0.7.dist-info/LICENSE
bshlocal-0.0.7.dist-info/METADATA
bshlocal-0.0.7.dist-info/WHEEL
bshlocal-0.0.7.dist-info/top_level.txt
bshlocal-0.0.7.dist-info/RECORD
