Metadata-Version: 2.1
Name: bshlocal
Version: 0.0.7
Summary: Bosch Smart Home Local API Python Library
Home-page: https://github.com/cabrust/bshlocal
Author: Clemens-Alexander Brust
Author-email: cabrust@pm.me
License: UNKNOWN
Platform: UNKNOWN
Classifier: Programming Language :: Python :: 3
Classifier: License :: OSI Approved :: BSD License
Classifier: Operating System :: OS Independent
Requires-Python: >=3.7
Requires-Dist: requests (==2.22)
